modi_firmware_updater/__init__.py
modi_firmware_updater/__main__.py
modi_firmware_updater/gui_firmware_updater.py
modi_firmware_updater/core/__init__.py
modi_firmware_updater/core/esp32_updater.py
modi_firmware_updater/core/gd32_updater.py
modi_firmware_updater/core/stm32_updater.py
modi_firmware_updater/util/__init__.py
modi_firmware_updater/util/connection_util.py
modi_firmware_updater/util/message_util.py
modi_firmware_updater/util/module_util.py
modi_firmware_updater-0.1.0.dist-info/LICENSE
modi_firmware_updater-0.1.0.dist-info/METADATA
modi_firmware_updater-0.1.0.dist-info/WHEEL
modi_firmware_updater-0.1.0.dist-info/top_level.txt
modi_firmware_updater-0.1.0.dist-info/RECORD
