Metadata-Version: 2.1
Name: modi-firmware-updater
Version: 0.1.0
Summary: A GUI Form of MODI Firmware Updater utilizing PyMODI as its backend.
Home-page: https://github.com/LUXROBO/modi-firmware-updater
Author: LUXROBO
Author-email: tech@luxrobo.com
License: MIT
Platform: UNKNOWN
Classifier: Programming Language :: Python :: 3
Classifier: License :: OSI Approved :: MIT License
Classifier: Operating System :: OS Independent
Requires-Dist: pyserial
Requires-Dist: pyqt5
Requires-Dist: pyinstaller
Requires-Dist: pytest
Requires-Dist: mypy
Requires-Dist: flake8
Requires-Dist: isort
